blender/__init__.py
blender/_data.py
blender/default_cfg.py
blender/pie.py
blender/pie_chart_tut.py
blender/blenderpy/__init__.py
blender/blenderpy/graph.py
blender/blenderpy/handler.py
blender/blenderpy/util.py
blender/blenderpy/templates/__init__.py
blender/blenderpy/templates/bargraphrace.py
blender/config/__init__.py
blender/config/config.py
tests/__init__.py
tests/test_bar_chart_race.py
fsm_blender-0.0.22.dist-info/METADATA
fsm_blender-0.0.22.dist-info/WHEEL
fsm_blender-0.0.22.dist-info/top_level.txt
fsm_blender-0.0.22.dist-info/RECORD
