Metadata-Version: 2.1
Name: fsm-blender
Version: 0.0.22
Summary: Data Driven Content Creation in Blender
Home-page: UNKNOWN
Author: Philip Paprotny
Author-email: <philip.paprotny@gmail.com>
License: UNKNOWN
Keywords: python,blender,datavis
Platform: UNKNOWN
Classifier: Development Status :: 3 - Alpha
Classifier: Intended Audience :: Education
Classifier: License :: OSI Approved :: MIT License
Classifier: Programming Language :: Python :: 3
Classifier: Programming Language :: Python :: 3.9
Requires-Dist: numpy (==1.21.5)
Requires-Dist: pandas (==1.4.2)
Requires-Dist: pytest (==7.1.1)
Requires-Dist: setuptools (==62.1.0)
